prompture/__init__.py
prompture/_version.py
prompture/agent.py
prompture/agent_types.py
prompture/async_agent.py
prompture/async_conversation.py
prompture/async_core.py
prompture/async_driver.py
prompture/async_groups.py
prompture/cache.py
prompture/callbacks.py
prompture/cli.py
prompture/conversation.py
prompture/core.py
prompture/cost_mixin.py
prompture/discovery.py
prompture/driver.py
prompture/field_definitions.py
prompture/group_types.py
prompture/groups.py
prompture/image.py
prompture/ledger.py
prompture/logging.py
prompture/model_rates.py
prompture/persistence.py
prompture/persona.py
prompture/runner.py
prompture/serialization.py
prompture/server.py
prompture/session.py
prompture/settings.py
prompture/tools.py
prompture/tools_schema.py
prompture/validator.py
prompture/aio/__init__.py
prompture/drivers/__init__.py
prompture/drivers/airllm_driver.py
prompture/drivers/async_airllm_driver.py
prompture/drivers/async_azure_driver.py
prompture/drivers/async_claude_driver.py
prompture/drivers/async_google_driver.py
prompture/drivers/async_grok_driver.py
prompture/drivers/async_groq_driver.py
prompture/drivers/async_hugging_driver.py
prompture/drivers/async_lmstudio_driver.py
prompture/drivers/async_local_http_driver.py
prompture/drivers/async_modelscope_driver.py
prompture/drivers/async_moonshot_driver.py
prompture/drivers/async_ollama_driver.py
prompture/drivers/async_openai_driver.py
prompture/drivers/async_openrouter_driver.py
prompture/drivers/async_registry.py
prompture/drivers/async_zai_driver.py
prompture/drivers/azure_driver.py
prompture/drivers/claude_driver.py
prompture/drivers/google_driver.py
prompture/drivers/grok_driver.py
prompture/drivers/groq_driver.py
prompture/drivers/hugging_driver.py
prompture/drivers/lmstudio_driver.py
prompture/drivers/local_http_driver.py
prompture/drivers/modelscope_driver.py
prompture/drivers/moonshot_driver.py
prompture/drivers/ollama_driver.py
prompture/drivers/openai_driver.py
prompture/drivers/openrouter_driver.py
prompture-0.0.42.dist-info/licenses/LICENSE
prompture-0.0.42.dist-info/METADATA
prompture-0.0.42.dist-info/WHEEL
prompture-0.0.42.dist-info/entry_points.txt
prompture-0.0.42.dist-info/top_level.txt
prompture-0.0.42.dist-info/RECORD
