Metadata-Version: 2.4
Name: prompture
Version: 0.0.42
Summary: Ask LLMs to return structured JSON and run cross-model tests. API-first.
Author-email: Juan Denis <juan@vene.co>
License-Expression: MIT
Project-URL: Homepage, https://github.com/jhd3197/prompture
Classifier: Programming Language :: Python :: 3
Classifier: Operating System :: OS Independent
Requires-Python: >=3.9
License-File: LICENSE
Requires-Dist: anthropic>=0.8.0
Requires-Dist: click>=8.0
Requires-Dist: google-generativeai>=0.3.0
Requires-Dist: groq>=0.4.0
Requires-Dist: httpx>=0.25.0
Requires-Dist: jsonschema>=4.0
Requires-Dist: openai>=1.0.0
Requires-Dist: pandas>=1.3.0
Requires-Dist: pydantic>=1.10
Requires-Dist: pydantic-settings>=2.0
Requires-Dist: python-dotenv>=0.19.0
Requires-Dist: python-toon>=0.1.0
Requires-Dist: requests>=2.28
Requires-Dist: python-dateutil>=2.9.0
Requires-Dist: tukuy>=0.0.6
Requires-Dist: pyyaml>=6.0
Provides-Extra: test
Requires-Dist: pytest>=7.0; extra == "test"
Requires-Dist: pytest-asyncio>=0.23.0; extra == "test"
Provides-Extra: dev
Requires-Dist: pytest>=7.0; extra == "dev"
Requires-Dist: pytest-asyncio>=0.23.0; extra == "dev"
Requires-Dist: ruff>=0.8.0; extra == "dev"
Provides-Extra: airllm
Requires-Dist: airllm>=2.8.0; extra == "airllm"
Provides-Extra: redis
Requires-Dist: redis>=4.0; extra == "redis"
Provides-Extra: serve
Requires-Dist: fastapi>=0.100; extra == "serve"
Requires-Dist: uvicorn[standard]>=0.20; extra == "serve"
Requires-Dist: sse-starlette>=1.6; extra == "serve"
Provides-Extra: scaffold
Requires-Dist: jinja2>=3.0; extra == "scaffold"
Dynamic: license-file
